{
        "customers":
        [
                {
                        "id": 1,
                        "name": "CUS 1"
                },
                {
                        "id": 2,
                        "name": "CUS 2"
                },
                {
                        "id": 3,
                        "name": "CUS 3"
                },
                {
                        "id": 4,
                        "name": "CUS 4"
                },
                {
                        "id": 5,
                        "name": "CUS 5"
                }
        ],
        "users":
        [
                {
                        "id": 888,
                        "name": "Yan Boucher Bouchard",
                        "company": "Globe Technologie",
                        "authority": "developpeur"
                },
                {
                        "id": 123,
                        "name": "Jean Côté",
                        "company": "Béton Chevalier",
                        "authority": "acheteur"
                },
                {
                        "id": 321,
                        "name": "Jeanne Tremblay",
                        "company": "Béton JFK",
                        "authority": "vendeur"
                },
                {
                        "id": 111,
                        "name": "Luc Poitras",
                        "company": "RCI",
                        "authority": "invité"
                }
        ]
        "profile":
        {
                "name": "typicode"
        }
    }
